<Properties StartupConfiguration="{83BE2866-0A53-71D6-C680-423D67BBAD46}|">
  <MonoDevelop.Ide.Workbench ActiveDocument="Assets/Scripts/BoxInvUIText.cs">
    <Files>
      <File FileName="Assets/Scripts/GenBar.cs" Line="1" Column="1" IsPinned="True" />
      <File FileName="Assets/Scripts/Door.cs" Line="48" Column="2" IsPinned="True" />
      <File FileName="Assets/Scripts/HPBar.cs" IsPinned="True" />
      <File FileName="Assets/Scripts/Player.cs" />
      <File FileName="Assets/Scripts/ScoreKeeper.cs" />
      <File FileName="Assets/Scripts/PickUp.cs" />
      <File FileName="Assets/Scripts/Inv_Box.cs" />
      <File FileName="Assets/Scripts/Shield_Gen.cs" />
      <File FileName="Assets/Scripts/Inventory.cs" Line="20" Column="53" />
      <File FileName="Assets/Scripts/LvlTracker.cs" />
      <File FileName="Assets/Scripts/GunOn.cs" />
      <File FileName="Assets/Scripts/HUB_TV.cs" />
      <File FileName="Assets/Scripts/TV_Counter.cs" />
      <File FileName="Assets/Scripts/Resetter.cs" />
      <File FileName="Assets/Scripts/BoxInvUIText.cs" Line="1" Column="1" />
      <File FileName="Assets/Scripts/InvTracker.cs" />
      <File FileName="Assets/Scripts/Lance.cs" />
      <File FileName="Assets/Scripts/RegularGun.cs" />
      <File FileName="Assets/Scripts/RegularSword.cs" />
      <File FileName="Assets/Scripts/RocketLauncher.cs" />
      <File FileName="Assets/Scripts/Bomb.cs" />
      <File FileName="Assets/Scripts/LaserGun.cs" />
      <File FileName="Assets/Scripts/PlatformGoUnder.cs" />
      <File FileName="Assets/Scripts/RandomWeapon.cs" />
      <File FileName="Assets/Scripts/Text_disp.cs" />
      <File FileName="Assets/Scripts/Progressor.cs" />
      <File FileName="Assets/Scripts/LevelManager.cs" />
      <File FileName="Assets/Scripts/Lightning.cs" Line="16" Column="6" />
      <File FileName="Assets/Scripts/GunRobot.cs" />
      <File FileName="Assets/Scripts/Conductor.cs" />
      <File FileName="Assets/Scripts/Warning.cs" />
      <File FileName="Assets/Scripts/ConductorCircle.cs" />
      <File FileName="Assets/Scripts/SwordRobot.cs" Line="73" Column="2" NotebookId="1" />
      <File FileName="Assets/Scripts/Informant.cs" NotebookId="1" />
    </Files>
  </MonoDevelop.Ide.Workbench>
  <MonoDevelop.Ide.DebuggingService.PinnedWatches />
  <MonoDevelop.Ide.Workspace ActiveConfiguration="Debug" />
  <MonoDevelop.Ide.ItemProperties.Assembly-CSharp PreferredExecutionTarget="9c34631d-8a05-4b00-8e38-9c3f3b0992ea" />
  <MonoDevelop.Ide.DebuggingService.Breakpoints>
    <BreakpointStore />
  </MonoDevelop.Ide.DebuggingService.Breakpoints>
  <MultiItemStartupConfigurations />
</Properties>